CHANGES.txt
MANIFEST.in
README.txt
setup.py
Products/__init__.py
Products.CMFTestCase.egg-info/PKG-INFO
Products.CMFTestCase.egg-info/SOURCES.txt
Products.CMFTestCase.egg-info/dependency_links.txt
Products.CMFTestCase.egg-info/namespace_packages.txt
Products.CMFTestCase.egg-info/not-zip-safe
Products.CMFTestCase.egg-info/requires.txt
Products.CMFTestCase.egg-info/top_level.txt
Products/CMFTestCase/CMFTestCase.py
Products/CMFTestCase/THIS_AREA_IS_CLOSED.txt
Products/CMFTestCase/VERSION.txt
Products/CMFTestCase/__init__.py
Products/CMFTestCase/ctc.py
Products/CMFTestCase/five.py
Products/CMFTestCase/framework.py
Products/CMFTestCase/interfaces.py
Products/CMFTestCase/layer.py
Products/CMFTestCase/runalltests.py
Products/CMFTestCase/setup.py
Products/CMFTestCase/testCMFCalendar.py
Products/CMFTestCase/testCMFTestCase.py
Products/CMFTestCase/testDocument.py
Products/CMFTestCase/testInterfaces.py
Products/CMFTestCase/testMembershipTool.py
Products/CMFTestCase/testSkeleton.py
Products/CMFTestCase/tests.py
Products/CMFTestCase/utils.py