Metadata-Version: 1.0
Name: Products.CMFTestCase
Version: 0.9.12
Summary: Integration testing framework for CMF.
Home-page: http://plone.org/products/cmftestcase
Author: Stefan H. Holek
Author-email: stefan@epy.co.at
License: ZPL
Keywords: cmf testing
Platform: UNKNOWN
Classifier: Framework :: Zope2
Classifier: Programming Language :: Python
